{
  "scores": [
    {
      "id": 1,
      "Name": "Test",
      "PlanetsCleared": 0,
      "LivesRemaining": 0
    },
    {
      "Name": "Mark Cuban",
      "PlanetsClearead": 5,
      "LivesRemaining": 1,
      "id": 2
    },
    {
      "Name": "Tyrone Cloma",
      "PlanetsClearead": 1,
      "LivesRemaining": 5,
      "id": 3
    },
    {
      "Name": "Barney",
      "PlanetsClearead": 0,
      "LivesRemaining": 5,
      "id": 4
    },
    {
      "Name": "Wawwa",
      "PlanetsClearead": 0,
      "LivesRemaining": 5,
      "id": 5
    },
    {
      "Name": "Submit me",
      "PlanetsClearead": 0,
      "LivesRemaining": 5,
      "id": 6
    },
    {
      "Name": "Meemaw",
      "PlanetsClearead": 0,
      "LivesRemaining": 5,
      "id": 7
    },
    {
      "Name": "Mark",
      "PlanetsClearead": 0,
      "LivesRemaining": 5,
      "id": 8
    },
    {
      "Name": "Cuban",
      "PlanetsClearead": 0,
      "LivesRemaining": 5,
      "id": 9
    },
    {
      "Name": "Beedo",
      "PlanetsClearead": 0,
      "LivesRemaining": 5,
      "id": 10
    },
    {
      "Name": "Fuck",
      "PlanetsClearead": 0,
      "LivesRemaining": 5,
      "id": 11
    },
    {
      "Name": "Donald",
      "PlanetsClearead": 0,
      "LivesRemaining": 5,
      "id": 12
    },
    {
      "Name": "The duck",
      "PlanetsClearead": 0,
      "LivesRemaining": 5,
      "id": 13
    },
    {
      "Name": "",
      "PlanetsClearead": 0,
      "LivesRemaining": 5,
      "id": 14
    },
    {
      "Name": "",
      "PlanetsClearead": 0,
      "LivesRemaining": 5,
      "id": 15
    },
    {
      "Name": "",
      "PlanetsClearead": 0,
      "LivesRemaining": 5,
      "id": 16
    },
    {
      "Name": "Emoji test",
      "PlanetsClearead": "",
      "LivesRemaining": "❤️❤️❤️❤️❤️",
      "id": 17
    },
    {
      "Name": "Bob",
      "PlanetsClearead": "",
      "LivesRemaining": "❤️❤️❤️❤️❤️",
      "id": 18
    },
    {
      "Name": "aaa",
      "PlanetsClearead": "",
      "LivesRemaining": "❤️❤️❤️❤️❤️",
      "id": 19
    },
    {
      "Name": "stay",
      "PlanetsClearead": "",
      "LivesRemaining": "❤️❤️❤️❤️❤️",
      "id": 20
    },
    {
      "Name": "a",
      "PlanetsClearead": "",
      "LivesRemaining": "❤️❤️❤️❤️❤️",
      "id": 21
    }
  ]
}